ii_django_backup
ii_django_backup/management
