Metadata-Version: 1.1
Name: ii-django-backup
Version: 0.3
Summary: ideallical django backup
Home-page: https://github.com/ideallical/ii-django-backup
Author: ideallical
Author-email: info@ideallical.com
License: BSD
Download-URL: https://github.com/ideallical/ii-django-backup/archive/0.3.tar.gz
Keywords: django,backup,dropbox
Platform: UNKNOWN
